test_oglop_proj_b/__init__.py
test_oglop_proj_b-0.1.0.dist-info/WHEEL
test_oglop_proj_b-0.1.0.dist-info/METADATA
test_oglop_proj_b-0.1.0.dist-info/RECORD
